{
    "/participate":"/resiway.fr#!/association/participer",
    "/association/:any?":"/resiway.fr#!/association/:any",    
    "/resiexchange":"/resiexchange.fr",
    "/resiway":"/resiway.fr",
    "/resilib":"/resilib.fr",   
    "/resiexchange.fr/question/:id/:title?":"/resiexchange.fr#!/question/:id/:title?",
    "/resilib.fr/document/:id/:title?":"/resilib.fr#!/document/:id/:title?",
    "/resiexchange.fr/:any":"/resiexchange.fr",    
    "/resilib.fr/:any":"/resilib.fr",
    "/resiway.fr/:any":"/resiway.fr",    
    "/questions/:any?":"/resiexchange.fr#!/questions",
    "/documents/:any?":"/resilib.fr#!/documents",
    "/articles/:any?":"/resipedia.fr#!/articles",
    "/question/:id/:title?":"/resiexchange.fr#!/question/:id/:title?",
    "/document/:id/:title?":"/resilib.fr#!/document/:id/:title?",
    "/article/:id/:title?":"/resipedia.fr#!/article/:id/:title?",
    "/author/:name":"/resilib.fr#!/author/:name",
    "/user/confirm/:code":"/resiexchange.fr#!/user/confirm/:code",
    "/user/password/:code":"/resiexchange.fr#!/user/password/:code",
    "/user/sign/up":"/resiexchange.fr#!/user/sign/up",    
    "/user/:id/:name?":"/resiexchange.fr#!/user/:id/:name",
    "/help/category/:id/:title?":"/resiexchange.fr#!/help/category/:id/:title?",
    "/meta.resiexchange.fr":"?show=resiway_meta.resiexchange.fr",    
    "/resiexchange.fr":"?show=resiway_resiexchange.fr",    
    "/resiway.fr":"?show=resiway_resiway.fr",
    "/resilib.fr":"?show=resiway_resilib.fr",
    "/ekopedia.fr":"?show=resiway_ekopedia.fr",
    "/resipedia.fr":"?show=resipedia_resipedia.fr",    
    "/sitemap.txt":"?show=resiway_sitemap",
    "/sitemap.html":"?show=resiway_sitemap&output=html",
    "/api/categories":"?get=resiway_category_list&api=1.0",
    "/api/questions":"?get=resiway_api&class=question",
    "/api/documents":"?get=resiway_api&class=document",
    "/api/articles":"?get=resiway_api&class=article",
    "/pdf/question/:id/:title?":"?get=resiway_pdf&class=question",
    "/pdf/document/:id/:title?":"?get=resiway_pdf&class=document",
    "/pdf/article/:id/:title?":"?get=resiway_pdf&class=article",
    "/html/question/:id/:title?":"?get=resiway_html&class=question",
    "/html/document/:id/:title?":"?get=resiway_html&class=document",
    "/html/article/:id/:title?":"?get=resiway_html&class=article",
    "/oauth2callback":"?show=resiway_oauth"
}